aixen/__init__.py
aixen/_version.py
aixen/context.py
aixen/apis/__init__.py
aixen/apis/chat.py
aixen/apis/chat_pricing.json
aixen/apis/image.py
aixen/apis/voice.py
aixen-0.1.1.dist-info/LICENSE
aixen-0.1.1.dist-info/METADATA
aixen-0.1.1.dist-info/WHEEL
aixen-0.1.1.dist-info/top_level.txt
aixen-0.1.1.dist-info/RECORD
