Metadata-Version: 2.1
Name: aixen
Version: 0.1.1
Summary: A framework for AI engineering
Author-email: Peter Romov <peter@romov.com>
License: Apache License
Project-URL: Homepage, https://github.com/romovpa/aixen
Project-URL: Repository, https://github.com/romovpa/aixen
Project-URL: Issue Tracker, https://github.com/romovpa/aixen/issues
Classifier: Programming Language :: Python :: 3
Classifier: License :: OSI Approved :: Apache Software License
Requires-Python: >=3.9
License-File: LICENSE
Requires-Dist: pydantic ~=2.8
Requires-Dist: httpx ~=0.27
Requires-Dist: python-dotenv ~=1.0
Requires-Dist: python-slugify ~=8.0
Requires-Dist: loguru ~=0.7
Requires-Dist: openai ~=1.35
Requires-Dist: replicate ~=0.26
